nbclass/__init__.py
nbclass/common.py
nbclass/console.py
nbclass/create.py
nbclass/decorators.py
nbclass/email_sender.py
nbclass/geo_transform.py
nbclass/log.py
nbclass/tools.py
nbclass/typeshed.py
nbclass/db/__init__.py
nbclass/db/mongodb.py
nbclass/db/mysqldb.py
nbclass/db/redis_lock.py
nbclass/db/redisdb.py
nbclass/encrypt/__init__.py
nbclass/encrypt/aes.py
nbclass/encrypt/func.py
nbclass/encrypt/hmac.py
nbclass/encrypt/rsa.py
nbclass/encrypt/sm2.py
nbclass/encrypt/sm3.py
nbclass/encrypt/sm4.py
nbclass/network/__init__.py
nbclass/network/user_pool/__init__.py
nbclass/network/user_pool/base_user_pool.py
nbclass/network/user_pool/normal_user_pool.py
test/__init__.py
test/test.py
test/test_encrypt.py
nbclass-1.5.1.dist-info/LICENSE
nbclass-1.5.1.dist-info/METADATA
nbclass-1.5.1.dist-info/WHEEL
nbclass-1.5.1.dist-info/top_level.txt
nbclass-1.5.1.dist-info/RECORD
