Metadata-Version: 2.1
Name: nbclass
Version: 1.5.1
Summary: nbclass工具包
Author: XiaoBai
Author-email: 1808269437@qq.com
License: MIT
Classifier: Programming Language :: Python :: 3
Requires-Python: >=3.6
License-File: LICENSE
Requires-Dist: DBUtils (>=3.0.3)
Requires-Dist: loguru (>=0.6.0)
Requires-Dist: openpyxl (>=3.1.2)
Requires-Dist: prettytable (>=3.11.0)
Requires-Dist: pycryptodome (>=3.17)
Requires-Dist: PyExecJS (>=1.5.1)
Requires-Dist: pymongo (>=4.7.2)
Requires-Dist: PyMySQL (>=1.0.2)
Requires-Dist: redis (>=3.5.3)
Requires-Dist: tqdm (>=4.65.0)
Requires-Dist: xlrd (>=2.0.1)
Requires-Dist: xlutils (>=2.0.0)
Requires-Dist: xlwt (>=1.3.0)
Requires-Dist: shapely (>=2.0.1)
Provides-Extra: all
Requires-Dist: redis-py-cluster (>=2.1.0) ; extra == 'all'
Provides-Extra: render
